city_of_gold/__init__.py
city_of_gold/_city_of_gold.cpython-38-darwin.so
city_of_gold/assets/player.xcf
city_of_gold/assets/player.bmp
city_of_gold/assets/hexes/water.bmp
city_of_gold/assets/hexes/rubble.bmp
city_of_gold/assets/hexes/jungle.bmp
city_of_gold/assets/hexes/basecamp.bmp
city_of_gold/assets/hexes/jungle.xcf
city_of_gold/assets/hexes/desert.bmp
city_of_gold/assets/requires/remove.bmp
city_of_gold/assets/requires/coin.xcf
city_of_gold/assets/requires/coin.bmp
city_of_gold/assets/requires/remove.xcf
city_of_gold/assets/requires/machete.bmp
city_of_gold/assets/requires/paddle.xcf
city_of_gold/assets/requires/discard.xcf
city_of_gold/assets/requires/discard.bmp
city_of_gold/assets/requires/paddle.bmp
city_of_gold/assets/requires/machete.xcf
city_of_gold-0.0.3.dist-info/RECORD
city_of_gold-0.0.3.dist-info/WHEEL
city_of_gold-0.0.3.dist-info/METADATA
city_of_gold-0.0.3.dist-info/licenses/LICENSE
