Metadata-Version: 2.4
Name: city_of_gold
Version: 0.0.3
Summary: A board game reinforcement learning enviroment in C++
Author-Email: =?utf-8?q?Aapo_K=C3=B6ssi?= <aapo.ilmari.kossi@cern.ch>
License-Expression: Apache-2.0
License-File: LICENSE
Project-URL: homepage, https://github.com/aapo-kossi/city-of-gold
Project-URL: issues, https://github.com/aapo-kossi/city-of-gold/issues
Requires-Python: >=3.8
Requires-Dist: numpy
